bert_classifier/__init__.py
bert_classifier/bert.py
bert_classifier/data.py
bert_classifier/io.py
bert_classifier/metrics.py
bert_classifier/predict.py
bert_classifier/train.py
bert_classifier-0.1.18.dist-info/LICENSE
bert_classifier-0.1.18.dist-info/METADATA
bert_classifier-0.1.18.dist-info/WHEEL
bert_classifier-0.1.18.dist-info/top_level.txt
bert_classifier-0.1.18.dist-info/RECORD
