Metadata-Version: 2.1
Name: bert-classifier
Version: 0.1.18
Summary: Transformers based NLP classification models
Home-page: https://github.com/minggnim/nlp-classification-model
Author: Ming Gao
Author-email: ming_gao@outlook.com
Classifier: Programming Language :: Python :: 3
Classifier: License :: OSI Approved :: GNU General Public License v3 (GPLv3)
Classifier: Operating System :: OS Independent
Requires-Python: >=3.6
License-File: LICENSE
Requires-Dist: torch
Requires-Dist: transformers
Provides-Extra: full
Requires-Dist: tqdm ; extra == 'full'
